{
  "resolvedId": "C:/Users/MSII/Desktop/pj/dansavanh/node_modules/ant-design-vue/es/vc-select/hooks/useCache.js",
  "transforms": [
    {
      "name": "vite:load-fallback",
      "result": "import _extends from \"@babel/runtime/helpers/esm/extends\";\nimport { shallowRef, computed } from 'vue';\n/**\n * Cache `value` related LabeledValue & options.\n */\nexport default ((labeledValues, valueOptions) => {\n  const cacheRef = shallowRef({\n    values: new Map(),\n    options: new Map()\n  });\n  const filledLabeledValues = computed(() => {\n    const {\n      values: prevValueCache,\n      options: prevOptionCache\n    } = cacheRef.value;\n    // Fill label by cache\n    const patchedValues = labeledValues.value.map(item => {\n      var _a;\n      if (item.label === undefined) {\n        return _extends(_extends({}, item), {\n          label: (_a = prevValueCache.get(item.value)) === null || _a === void 0 ? void 0 : _a.label\n        });\n      }\n      return item;\n    });\n    // Refresh cache\n    const valueCache = new Map();\n    const optionCache = new Map();\n    patchedValues.forEach(item => {\n      valueCache.set(item.value, item);\n      optionCache.set(item.value, valueOptions.value.get(item.value) || prevOptionCache.get(item.value));\n    });\n    cacheRef.value.values = valueCache;\n    cacheRef.value.options = optionCache;\n    return patchedValues;\n  });\n  const getOption = val => valueOptions.value.get(val) || cacheRef.value.options.get(val);\n  return [filledLabeledValues, getOption];\n});",
      "start": 1718517099485,
      "end": 1718517099534,
      "sourcemaps": null
    },
    {
      "name": "nuxt:layer-aliasing",
      "start": 1718517099534,
      "end": 1718517099534,
      "order": "pre"
    },
    {
      "name": "nuxt:server-devonly:transform",
      "start": 1718517099534,
      "end": 1718517099534,
      "order": "pre"
    },
    {
      "name": "unplugin-vue-i18n",
      "start": 1718517099534,
      "end": 1718517099534,
      "order": "pre"
    },
    {
      "name": "nuxtjs:i18n-macros-transform",
      "start": 1718517099534,
      "end": 1718517099534,
      "order": "pre"
    },
    {
      "name": "nuxt:client-fallback-auto-id",
      "start": 1718517099534,
      "end": 1718517099534,
      "order": "pre"
    },
    {
      "name": "vite:css",
      "start": 1718517099534,
      "end": 1718517099534,
      "order": "normal"
    },
    {
      "name": "vite:esbuild",
      "start": 1718517099534,
      "end": 1718517099534,
      "order": "normal"
    },
    {
      "name": "vite:json",
      "start": 1718517099534,
      "end": 1718517099534,
      "order": "normal"
    },
    {
      "name": "vite:worker",
      "start": 1718517099534,
      "end": 1718517099534,
      "order": "normal"
    },
    {
      "name": "vite:vue",
      "start": 1718517099534,
      "end": 1718517099534,
      "order": "normal"
    },
    {
      "name": "vite:vue-jsx",
      "start": 1718517099534,
      "end": 1718517099534,
      "order": "normal"
    },
    {
      "name": "replace",
      "start": 1718517099534,
      "end": 1718517099534,
      "order": "normal"
    },
    {
      "name": "nuxt:remove-plugin-metadata",
      "start": 1718517099534,
      "end": 1718517099534,
      "order": "normal"
    },
    {
      "name": "nuxt:chunk-error",
      "start": 1718517099534,
      "end": 1718517099534,
      "order": "normal"
    },
    {
      "name": "nuxt:components:imports",
      "start": 1718517099534,
      "end": 1718517099534,
      "order": "normal"
    },
    {
      "name": "replace",
      "start": 1718517099534,
      "end": 1718517099534,
      "order": "normal"
    },
    {
      "name": "ssr-styles",
      "start": 1718517099534,
      "end": 1718517099534,
      "order": "normal"
    },
    {
      "name": "vite:define",
      "start": 1718517099534,
      "end": 1718517099534,
      "order": "normal"
    },
    {
      "name": "vite:css-post",
      "start": 1718517099534,
      "end": 1718517099534,
      "order": "normal"
    },
    {
      "name": "vite:build-html",
      "start": 1718517099534,
      "end": 1718517099534,
      "order": "normal"
    },
    {
      "name": "vite:worker-import-meta-url",
      "start": 1718517099534,
      "end": 1718517099534,
      "order": "normal"
    },
    {
      "name": "vite:asset-import-meta-url",
      "start": 1718517099534,
      "end": 1718517099534,
      "order": "normal"
    },
    {
      "name": "commonjs",
      "start": 1718517099534,
      "end": 1718517099534,
      "order": "normal"
    },
    {
      "name": "vite:dynamic-import-vars",
      "start": 1718517099534,
      "end": 1718517099534,
      "order": "normal"
    },
    {
      "name": "vite:import-glob",
      "start": 1718517099534,
      "end": 1718517099534,
      "order": "normal"
    },
    {
      "name": "nuxt:composable-keys",
      "start": 1718517099534,
      "end": 1718517099534,
      "order": "post"
    },
    {
      "name": "nuxtjs:i18n-resource",
      "start": 1718517099534,
      "end": 1718517099534,
      "order": "post"
    },
    {
      "name": "nuxtjs:i18n-meta-deprecation",
      "start": 1718517099534,
      "end": 1718517099534,
      "order": "post"
    },
    {
      "name": "nuxt:imports-transform",
      "start": 1718517099534,
      "end": 1718517099534,
      "order": "post"
    },
    {
      "name": "unctx:transform",
      "start": 1718517099534,
      "end": 1718517099534,
      "order": "post"
    },
    {
      "name": "nuxt:pages-macros-transform",
      "start": 1718517099534,
      "end": 1718517099534,
      "order": "post"
    },
    {
      "name": "nuxt:runtime-paths-dep",
      "start": 1718517099534,
      "end": 1718517099534,
      "order": "post"
    },
    {
      "name": "nuxt:route-injection-plugin",
      "start": 1718517099534,
      "end": 1718517099534,
      "order": "post"
    },
    {
      "name": "nuxt:components-loader",
      "start": 1718517099534,
      "end": 1718517099534,
      "order": "post"
    },
    {
      "name": "nuxt:tree-shake-composables:transform",
      "start": 1718517099534,
      "end": 1718517099534,
      "order": "post"
    },
    {
      "name": "vite:build-import-analysis",
      "start": 1718517099534,
      "end": 1718517099534,
      "order": "normal"
    },
    {
      "name": "vite:reporter",
      "start": 1718517099534,
      "end": 1718517099534,
      "order": "normal"
    }
  ]
}
