{
  "resolvedId": "C:/Users/MSII/Desktop/pj/dansavanh/node_modules/ant-design-vue/es/input-number/src/hooks/useCursor.js",
  "transforms": [
    {
      "name": "vite:load-fallback",
      "result": "import { warning } from '../../../vc-util/warning';\nimport { ref } from 'vue';\n/**\n * Keep input cursor in the correct position if possible.\n * Is this necessary since we have `formatter` which may mass the content?\n */\nexport default function useCursor(inputRef, focused) {\n  const selectionRef = ref(null);\n  function recordCursor() {\n    // Record position\n    try {\n      const {\n        selectionStart: start,\n        selectionEnd: end,\n        value\n      } = inputRef.value;\n      const beforeTxt = value.substring(0, start);\n      const afterTxt = value.substring(end);\n      selectionRef.value = {\n        start,\n        end,\n        value,\n        beforeTxt,\n        afterTxt\n      };\n    } catch (e) {\n      // Fix error in Chrome:\n      // Failed to read the 'selectionStart' property from 'HTMLInputElement'\n      // http://stackoverflow.com/q/21177489/3040605\n    }\n  }\n  /**\n   * Restore logic:\n   *  1. back string same\n   *  2. start string same\n   */\n  function restoreCursor() {\n    if (inputRef.value && selectionRef.value && focused.value) {\n      try {\n        const {\n          value\n        } = inputRef.value;\n        const {\n          beforeTxt,\n          afterTxt,\n          start\n        } = selectionRef.value;\n        let startPos = value.length;\n        if (value.endsWith(afterTxt)) {\n          startPos = value.length - selectionRef.value.afterTxt.length;\n        } else if (value.startsWith(beforeTxt)) {\n          startPos = beforeTxt.length;\n        } else {\n          const beforeLastChar = beforeTxt[start - 1];\n          const newIndex = value.indexOf(beforeLastChar, start - 1);\n          if (newIndex !== -1) {\n            startPos = newIndex + 1;\n          }\n        }\n        inputRef.value.setSelectionRange(startPos, startPos);\n      } catch (e) {\n        warning(false, `Something warning of cursor restore. Please fire issue about this: ${e.message}`);\n      }\n    }\n  }\n  return [recordCursor, restoreCursor];\n}",
      "start": 1718517098231,
      "end": 1718517098321,
      "sourcemaps": null
    },
    {
      "name": "nuxt:layer-aliasing",
      "start": 1718517098321,
      "end": 1718517098321,
      "order": "pre"
    },
    {
      "name": "nuxt:server-devonly:transform",
      "start": 1718517098321,
      "end": 1718517098321,
      "order": "pre"
    },
    {
      "name": "unplugin-vue-i18n",
      "start": 1718517098321,
      "end": 1718517098321,
      "order": "pre"
    },
    {
      "name": "nuxtjs:i18n-macros-transform",
      "start": 1718517098321,
      "end": 1718517098321,
      "order": "pre"
    },
    {
      "name": "nuxt:client-fallback-auto-id",
      "start": 1718517098321,
      "end": 1718517098321,
      "order": "pre"
    },
    {
      "name": "vite:css",
      "start": 1718517098321,
      "end": 1718517098321,
      "order": "normal"
    },
    {
      "name": "vite:esbuild",
      "start": 1718517098321,
      "end": 1718517098321,
      "order": "normal"
    },
    {
      "name": "vite:json",
      "start": 1718517098321,
      "end": 1718517098321,
      "order": "normal"
    },
    {
      "name": "vite:worker",
      "start": 1718517098321,
      "end": 1718517098321,
      "order": "normal"
    },
    {
      "name": "vite:vue",
      "start": 1718517098321,
      "end": 1718517098321,
      "order": "normal"
    },
    {
      "name": "vite:vue-jsx",
      "start": 1718517098321,
      "end": 1718517098321,
      "order": "normal"
    },
    {
      "name": "replace",
      "start": 1718517098321,
      "end": 1718517098321,
      "order": "normal"
    },
    {
      "name": "nuxt:remove-plugin-metadata",
      "start": 1718517098321,
      "end": 1718517098321,
      "order": "normal"
    },
    {
      "name": "nuxt:chunk-error",
      "start": 1718517098321,
      "end": 1718517098321,
      "order": "normal"
    },
    {
      "name": "nuxt:components:imports",
      "start": 1718517098321,
      "end": 1718517098321,
      "order": "normal"
    },
    {
      "name": "replace",
      "start": 1718517098321,
      "end": 1718517098321,
      "order": "normal"
    },
    {
      "name": "ssr-styles",
      "start": 1718517098321,
      "end": 1718517098321,
      "order": "normal"
    },
    {
      "name": "vite:define",
      "start": 1718517098321,
      "end": 1718517098321,
      "order": "normal"
    },
    {
      "name": "vite:css-post",
      "start": 1718517098321,
      "end": 1718517098321,
      "order": "normal"
    },
    {
      "name": "vite:build-html",
      "start": 1718517098321,
      "end": 1718517098321,
      "order": "normal"
    },
    {
      "name": "vite:worker-import-meta-url",
      "start": 1718517098321,
      "end": 1718517098321,
      "order": "normal"
    },
    {
      "name": "vite:asset-import-meta-url",
      "start": 1718517098321,
      "end": 1718517098321,
      "order": "normal"
    },
    {
      "name": "commonjs",
      "start": 1718517098321,
      "end": 1718517098321,
      "order": "normal"
    },
    {
      "name": "vite:dynamic-import-vars",
      "start": 1718517098321,
      "end": 1718517098321,
      "order": "normal"
    },
    {
      "name": "vite:import-glob",
      "start": 1718517098321,
      "end": 1718517098321,
      "order": "normal"
    },
    {
      "name": "nuxt:composable-keys",
      "start": 1718517098321,
      "end": 1718517098321,
      "order": "post"
    },
    {
      "name": "nuxtjs:i18n-resource",
      "start": 1718517098321,
      "end": 1718517098321,
      "order": "post"
    },
    {
      "name": "nuxtjs:i18n-meta-deprecation",
      "start": 1718517098321,
      "end": 1718517098321,
      "order": "post"
    },
    {
      "name": "nuxt:imports-transform",
      "start": 1718517098321,
      "end": 1718517098321,
      "order": "post"
    },
    {
      "name": "unctx:transform",
      "start": 1718517098321,
      "end": 1718517098321,
      "order": "post"
    },
    {
      "name": "nuxt:pages-macros-transform",
      "start": 1718517098321,
      "end": 1718517098321,
      "order": "post"
    },
    {
      "name": "nuxt:runtime-paths-dep",
      "start": 1718517098321,
      "end": 1718517098321,
      "order": "post"
    },
    {
      "name": "nuxt:route-injection-plugin",
      "start": 1718517098321,
      "end": 1718517098321,
      "order": "post"
    },
    {
      "name": "nuxt:components-loader",
      "start": 1718517098321,
      "end": 1718517098321,
      "order": "post"
    },
    {
      "name": "nuxt:tree-shake-composables:transform",
      "start": 1718517098321,
      "end": 1718517098321,
      "order": "post"
    },
    {
      "name": "vite:build-import-analysis",
      "start": 1718517098321,
      "end": 1718517098321,
      "order": "normal"
    },
    {
      "name": "vite:reporter",
      "start": 1718517098321,
      "end": 1718517098321,
      "order": "normal"
    }
  ]
}
