{
  "resolvedId": "C:/Users/MSII/Desktop/pj/dansavanh/node_modules/ant-design-vue/es/collapse/CollapsePanel.js",
  "transforms": [
    {
      "name": "vite:load-fallback",
      "result": "import _objectSpread from \"@babel/runtime/helpers/esm/objectSpread2\";\nimport _extends from \"@babel/runtime/helpers/esm/extends\";\nimport { withDirectives as _withDirectives, resolveDirective as _resolveDirective, vShow as _vShow, createVNode as _createVNode } from \"vue\";\nimport PanelContent from './PanelContent';\nimport { initDefaultProps } from '../_util/props-util';\nimport { collapsePanelProps } from './commonProps';\nimport { defineComponent } from 'vue';\nimport Transition from '../_util/transition';\nimport classNames from '../_util/classNames';\nimport devWarning from '../vc-util/devWarning';\nimport useConfigInject from '../config-provider/hooks/useConfigInject';\nexport { collapsePanelProps };\nexport default defineComponent({\n  compatConfig: {\n    MODE: 3\n  },\n  name: 'ACollapsePanel',\n  inheritAttrs: false,\n  props: initDefaultProps(collapsePanelProps(), {\n    showArrow: true,\n    isActive: false,\n    onItemClick() {},\n    headerClass: '',\n    forceRender: false\n  }),\n  slots: Object,\n  // emits: ['itemClick'],\n  setup(props, _ref) {\n    let {\n      slots,\n      emit,\n      attrs\n    } = _ref;\n    devWarning(props.disabled === undefined, 'Collapse.Panel', '`disabled` is deprecated. Please use `collapsible=\"disabled\"` instead.');\n    const {\n      prefixCls\n    } = useConfigInject('collapse', props);\n    const handleItemClick = () => {\n      emit('itemClick', props.panelKey);\n    };\n    const handleKeyPress = e => {\n      if (e.key === 'Enter' || e.keyCode === 13 || e.which === 13) {\n        handleItemClick();\n      }\n    };\n    return () => {\n      var _a, _b;\n      const {\n        header = (_a = slots.header) === null || _a === void 0 ? void 0 : _a.call(slots),\n        headerClass,\n        isActive,\n        showArrow,\n        destroyInactivePanel,\n        accordion,\n        forceRender,\n        openAnimation,\n        expandIcon = slots.expandIcon,\n        extra = (_b = slots.extra) === null || _b === void 0 ? void 0 : _b.call(slots),\n        collapsible\n      } = props;\n      const disabled = collapsible === 'disabled';\n      const prefixClsValue = prefixCls.value;\n      const headerCls = classNames(`${prefixClsValue}-header`, {\n        [headerClass]: headerClass,\n        [`${prefixClsValue}-header-collapsible-only`]: collapsible === 'header',\n        [`${prefixClsValue}-icon-collapsible-only`]: collapsible === 'icon'\n      });\n      const itemCls = classNames({\n        [`${prefixClsValue}-item`]: true,\n        [`${prefixClsValue}-item-active`]: isActive,\n        [`${prefixClsValue}-item-disabled`]: disabled,\n        [`${prefixClsValue}-no-arrow`]: !showArrow,\n        [`${attrs.class}`]: !!attrs.class\n      });\n      let icon = _createVNode(\"i\", {\n        \"class\": \"arrow\"\n      }, null);\n      if (showArrow && typeof expandIcon === 'function') {\n        icon = expandIcon(props);\n      }\n      const panelContent = _withDirectives(_createVNode(PanelContent, {\n        \"prefixCls\": prefixClsValue,\n        \"isActive\": isActive,\n        \"forceRender\": forceRender,\n        \"role\": accordion ? 'tabpanel' : null\n      }, {\n        default: slots.default\n      }), [[_vShow, isActive]]);\n      const transitionProps = _extends({\n        appear: false,\n        css: false\n      }, openAnimation);\n      return _createVNode(\"div\", _objectSpread(_objectSpread({}, attrs), {}, {\n        \"class\": itemCls\n      }), [_createVNode(\"div\", {\n        \"class\": headerCls,\n        \"onClick\": () => !['header', 'icon'].includes(collapsible) && handleItemClick(),\n        \"role\": accordion ? 'tab' : 'button',\n        \"tabindex\": disabled ? -1 : 0,\n        \"aria-expanded\": isActive,\n        \"onKeypress\": handleKeyPress\n      }, [showArrow && icon, _createVNode(\"span\", {\n        \"onClick\": () => collapsible === 'header' && handleItemClick(),\n        \"class\": `${prefixClsValue}-header-text`\n      }, [header]), extra && _createVNode(\"div\", {\n        \"class\": `${prefixClsValue}-extra`\n      }, [extra])]), _createVNode(Transition, transitionProps, {\n        default: () => [!destroyInactivePanel || isActive ? panelContent : null]\n      })]);\n    };\n  }\n});",
      "start": 1718517097291,
      "end": 1718517097336,
      "sourcemaps": null
    },
    {
      "name": "nuxt:layer-aliasing",
      "start": 1718517097336,
      "end": 1718517097336,
      "order": "pre"
    },
    {
      "name": "nuxt:server-devonly:transform",
      "start": 1718517097336,
      "end": 1718517097336,
      "order": "pre"
    },
    {
      "name": "unplugin-vue-i18n",
      "start": 1718517097336,
      "end": 1718517097336,
      "order": "pre"
    },
    {
      "name": "nuxtjs:i18n-macros-transform",
      "start": 1718517097336,
      "end": 1718517097336,
      "order": "pre"
    },
    {
      "name": "nuxt:client-fallback-auto-id",
      "start": 1718517097336,
      "end": 1718517097336,
      "order": "pre"
    },
    {
      "name": "vite:css",
      "start": 1718517097336,
      "end": 1718517097336,
      "order": "normal"
    },
    {
      "name": "vite:esbuild",
      "start": 1718517097336,
      "end": 1718517097336,
      "order": "normal"
    },
    {
      "name": "vite:json",
      "start": 1718517097336,
      "end": 1718517097336,
      "order": "normal"
    },
    {
      "name": "vite:worker",
      "start": 1718517097336,
      "end": 1718517097336,
      "order": "normal"
    },
    {
      "name": "vite:vue",
      "start": 1718517097336,
      "end": 1718517097336,
      "order": "normal"
    },
    {
      "name": "vite:vue-jsx",
      "start": 1718517097336,
      "end": 1718517097336,
      "order": "normal"
    },
    {
      "name": "replace",
      "start": 1718517097336,
      "end": 1718517097336,
      "order": "normal"
    },
    {
      "name": "nuxt:remove-plugin-metadata",
      "start": 1718517097336,
      "end": 1718517097336,
      "order": "normal"
    },
    {
      "name": "nuxt:chunk-error",
      "start": 1718517097336,
      "end": 1718517097336,
      "order": "normal"
    },
    {
      "name": "nuxt:components:imports",
      "start": 1718517097336,
      "end": 1718517097336,
      "order": "normal"
    },
    {
      "name": "replace",
      "start": 1718517097336,
      "end": 1718517097336,
      "order": "normal"
    },
    {
      "name": "ssr-styles",
      "start": 1718517097336,
      "end": 1718517097336,
      "order": "normal"
    },
    {
      "name": "vite:define",
      "start": 1718517097336,
      "end": 1718517097336,
      "order": "normal"
    },
    {
      "name": "vite:css-post",
      "start": 1718517097336,
      "end": 1718517097336,
      "order": "normal"
    },
    {
      "name": "vite:build-html",
      "start": 1718517097336,
      "end": 1718517097336,
      "order": "normal"
    },
    {
      "name": "vite:worker-import-meta-url",
      "start": 1718517097336,
      "end": 1718517097336,
      "order": "normal"
    },
    {
      "name": "vite:asset-import-meta-url",
      "start": 1718517097336,
      "end": 1718517097336,
      "order": "normal"
    },
    {
      "name": "commonjs",
      "start": 1718517097336,
      "end": 1718517097336,
      "order": "normal"
    },
    {
      "name": "vite:dynamic-import-vars",
      "start": 1718517097336,
      "end": 1718517097336,
      "order": "normal"
    },
    {
      "name": "vite:import-glob",
      "start": 1718517097336,
      "end": 1718517097336,
      "order": "normal"
    },
    {
      "name": "nuxt:composable-keys",
      "start": 1718517097336,
      "end": 1718517097336,
      "order": "post"
    },
    {
      "name": "nuxtjs:i18n-resource",
      "start": 1718517097336,
      "end": 1718517097336,
      "order": "post"
    },
    {
      "name": "nuxtjs:i18n-meta-deprecation",
      "start": 1718517097336,
      "end": 1718517097336,
      "order": "post"
    },
    {
      "name": "nuxt:imports-transform",
      "start": 1718517097336,
      "end": 1718517097336,
      "order": "post"
    },
    {
      "name": "unctx:transform",
      "start": 1718517097336,
      "end": 1718517097336,
      "order": "post"
    },
    {
      "name": "nuxt:pages-macros-transform",
      "start": 1718517097336,
      "end": 1718517097336,
      "order": "post"
    },
    {
      "name": "nuxt:runtime-paths-dep",
      "start": 1718517097336,
      "end": 1718517097336,
      "order": "post"
    },
    {
      "name": "nuxt:route-injection-plugin",
      "start": 1718517097336,
      "end": 1718517097336,
      "order": "post"
    },
    {
      "name": "nuxt:components-loader",
      "start": 1718517097336,
      "end": 1718517097336,
      "order": "post"
    },
    {
      "name": "nuxt:tree-shake-composables:transform",
      "start": 1718517097336,
      "end": 1718517097336,
      "order": "post"
    },
    {
      "name": "vite:build-import-analysis",
      "start": 1718517097336,
      "end": 1718517097336,
      "order": "normal"
    },
    {
      "name": "vite:reporter",
      "start": 1718517097337,
      "end": 1718517097337,
      "order": "normal"
    }
  ]
}
