{
  "resolvedId": "C:/Users/MSII/Desktop/pj/dansavanh/node_modules/@ant-design/icons-svg/es/asn/ProfileFilled.js",
  "transforms": [
    {
      "name": "vite:load-fallback",
      "result": "// This icon file is generated automatically.\nvar ProfileFilled = { \"icon\": { \"tag\": \"svg\", \"attrs\": { \"viewBox\": \"64 64 896 896\", \"focusable\": \"false\" }, \"children\": [{ \"tag\": \"path\", \"attrs\": { \"d\": \"M880 112H144c-17.7 0-32 14.3-32 32v736c0 17.7 14.3 32 32 32h736c17.7 0 32-14.3 32-32V144c0-17.7-14.3-32-32-32zM380 696c-22.1 0-40-17.9-40-40s17.9-40 40-40 40 17.9 40 40-17.9 40-40 40zm0-144c-22.1 0-40-17.9-40-40s17.9-40 40-40 40 17.9 40 40-17.9 40-40 40zm0-144c-22.1 0-40-17.9-40-40s17.9-40 40-40 40 17.9 40 40-17.9 40-40 40zm304 272c0 4.4-3.6 8-8 8H492c-4.4 0-8-3.6-8-8v-48c0-4.4 3.6-8 8-8h184c4.4 0 8 3.6 8 8v48zm0-144c0 4.4-3.6 8-8 8H492c-4.4 0-8-3.6-8-8v-48c0-4.4 3.6-8 8-8h184c4.4 0 8 3.6 8 8v48zm0-144c0 4.4-3.6 8-8 8H492c-4.4 0-8-3.6-8-8v-48c0-4.4 3.6-8 8-8h184c4.4 0 8 3.6 8 8v48z\" } }] }, \"name\": \"profile\", \"theme\": \"filled\" };\nexport default ProfileFilled;\n",
      "start": 1718517097161,
      "end": 1718517097171,
      "sourcemaps": null
    },
    {
      "name": "nuxt:layer-aliasing",
      "start": 1718517097171,
      "end": 1718517097171,
      "order": "pre"
    },
    {
      "name": "nuxt:server-devonly:transform",
      "start": 1718517097171,
      "end": 1718517097171,
      "order": "pre"
    },
    {
      "name": "unplugin-vue-i18n",
      "start": 1718517097171,
      "end": 1718517097171,
      "order": "pre"
    },
    {
      "name": "nuxtjs:i18n-macros-transform",
      "start": 1718517097171,
      "end": 1718517097171,
      "order": "pre"
    },
    {
      "name": "nuxt:client-fallback-auto-id",
      "start": 1718517097171,
      "end": 1718517097171,
      "order": "pre"
    },
    {
      "name": "vite:css",
      "start": 1718517097171,
      "end": 1718517097171,
      "order": "normal"
    },
    {
      "name": "vite:esbuild",
      "start": 1718517097171,
      "end": 1718517097171,
      "order": "normal"
    },
    {
      "name": "vite:json",
      "start": 1718517097171,
      "end": 1718517097171,
      "order": "normal"
    },
    {
      "name": "vite:worker",
      "start": 1718517097171,
      "end": 1718517097171,
      "order": "normal"
    },
    {
      "name": "vite:vue",
      "start": 1718517097171,
      "end": 1718517097171,
      "order": "normal"
    },
    {
      "name": "vite:vue-jsx",
      "start": 1718517097171,
      "end": 1718517097171,
      "order": "normal"
    },
    {
      "name": "replace",
      "start": 1718517097171,
      "end": 1718517097171,
      "order": "normal"
    },
    {
      "name": "nuxt:remove-plugin-metadata",
      "start": 1718517097171,
      "end": 1718517097171,
      "order": "normal"
    },
    {
      "name": "nuxt:chunk-error",
      "start": 1718517097171,
      "end": 1718517097171,
      "order": "normal"
    },
    {
      "name": "nuxt:components:imports",
      "start": 1718517097171,
      "end": 1718517097171,
      "order": "normal"
    },
    {
      "name": "replace",
      "start": 1718517097171,
      "end": 1718517097171,
      "order": "normal"
    },
    {
      "name": "ssr-styles",
      "start": 1718517097171,
      "end": 1718517097171,
      "order": "normal"
    },
    {
      "name": "vite:define",
      "start": 1718517097171,
      "end": 1718517097171,
      "order": "normal"
    },
    {
      "name": "vite:css-post",
      "start": 1718517097171,
      "end": 1718517097171,
      "order": "normal"
    },
    {
      "name": "vite:build-html",
      "start": 1718517097171,
      "end": 1718517097171,
      "order": "normal"
    },
    {
      "name": "vite:worker-import-meta-url",
      "start": 1718517097171,
      "end": 1718517097171,
      "order": "normal"
    },
    {
      "name": "vite:asset-import-meta-url",
      "start": 1718517097171,
      "end": 1718517097171,
      "order": "normal"
    },
    {
      "name": "commonjs",
      "start": 1718517097171,
      "end": 1718517097171,
      "order": "normal"
    },
    {
      "name": "vite:dynamic-import-vars",
      "start": 1718517097171,
      "end": 1718517097171,
      "order": "normal"
    },
    {
      "name": "vite:import-glob",
      "start": 1718517097171,
      "end": 1718517097171,
      "order": "normal"
    },
    {
      "name": "nuxt:composable-keys",
      "start": 1718517097171,
      "end": 1718517097171,
      "order": "post"
    },
    {
      "name": "nuxtjs:i18n-resource",
      "start": 1718517097171,
      "end": 1718517097171,
      "order": "post"
    },
    {
      "name": "nuxtjs:i18n-meta-deprecation",
      "start": 1718517097171,
      "end": 1718517097171,
      "order": "post"
    },
    {
      "name": "nuxt:imports-transform",
      "start": 1718517097171,
      "end": 1718517097171,
      "order": "post"
    },
    {
      "name": "unctx:transform",
      "start": 1718517097171,
      "end": 1718517097171,
      "order": "post"
    },
    {
      "name": "nuxt:pages-macros-transform",
      "start": 1718517097171,
      "end": 1718517097171,
      "order": "post"
    },
    {
      "name": "nuxt:runtime-paths-dep",
      "start": 1718517097171,
      "end": 1718517097171,
      "order": "post"
    },
    {
      "name": "nuxt:route-injection-plugin",
      "start": 1718517097171,
      "end": 1718517097171,
      "order": "post"
    },
    {
      "name": "nuxt:components-loader",
      "start": 1718517097171,
      "end": 1718517097171,
      "order": "post"
    },
    {
      "name": "nuxt:tree-shake-composables:transform",
      "start": 1718517097171,
      "end": 1718517097171,
      "order": "post"
    },
    {
      "name": "vite:build-import-analysis",
      "start": 1718517097171,
      "end": 1718517097171,
      "order": "normal"
    },
    {
      "name": "vite:reporter",
      "start": 1718517097171,
      "end": 1718517097171,
      "order": "normal"
    }
  ]
}
